{
    "title":"test_heading",
    "rows":[
        {
            "title":"test_title_0",
            "description":"test_description_0",
            "imageHref":"test_image_0"
        },
        {
            "title":"test_title_1",
            "description":"test_description_1",
            "imageHref":"test_image_1"
        },
        {
            "title":"test_title_2",
            "description":"test_description_2",
            "imageHref":"test_image_2"
        },
        {
            "title":"test_title_3",
            "description":"test_description_3",
            "imageHref":"test_image_3"
        }
        ]
}
